Workbook

Sheet README
B1: Yedi + Tidal — MVP & Phase 2 Work Breakdown Structure (WBS)
B2: Internal - Sotatek presale - source-grounded (audit Jul 8) - formula-driven, recalcs from the Rates sheet.
B4: STRUCTURE: Phase (MVP / Phase 2) -> EPIC -> Feature -> Sub-Feature -> Function. Each function = base CODING md per discipline (Backend/Mobile/Web).
B6: MODEL (all formula-driven):
B7: 1. Base Coding = BE + Mobile + Web (raw, pre-AI).
B8: 2. AI Reduction % per Task Type ('AI Factors') -> Adjusted Coding.
B9: 3. Delivery Efficiency factor (Rates!B21 = 0.70) applied = client-directed 30% compression on top of AI-assist.
B10: 4. Effort ratio 10/10/50/30: Total = Adjusted Coding / 50% x Efficiency. Spec=10%, PM=10%, Testing=30% derived from Total.
B11: 5. Cost = Coding x Dev-rate + Spec x BA + PM x PM + Testing x QC (day-rate = monthly / man-month days).
B12: 6. Contingency % added on Summary for grand total.
B14: RISK NOTE on the 0.70 efficiency factor:
B15: The 30% reduction is a business-directed compression requested to hit a 1.5-2 month MVP. It is ON TOP of AI-assisted reductions already baked into 'AI Factors'.
... B22: SHEETS: Rates | AI Factors | WBS | Summary | Missing-Features Checklist | Self-Review

Sheet Rates
A1: RATES & GLOBAL INPUTS (edit yellow cells)
A3: Man-month (working days) | B3: 20
A5: Role monthly rate | C5: Day-rate (=monthly/MM)
A6: Developer (BE/Mobile/Web) | B6: 3000 | D6: =B6/$B$3
A7: QC | B7: 2800 | D7: =B7/$B$3
A8: Project Manager | B8: 3600 | D8: =B8/$B$3
A9: BA & Designer | B9: 3000 | D9: =B9/$B$3
A10: DevOps | B10: 3400 | D10: =B10/$B$3
A12: Effort ratio
A13: Spec % | B13: 0.1
A14: PM % | B14: 0.1
A15: Coding % | B15: 0.5
A16: Testing % | B16: 0.3
A17: Ratio check | B17: =B13+B14+B15+B16
A19: Contingency % | B19: 0.12
A21: Delivery Efficiency factor | B21: 0.7
A22: (1.00 = no cut; 0.70 = -30% client-directed)

Sheet AI Factors
A1: AI-Assisted Development - Effort Reduction by Task Type
A2: Task Type | B2: AI Reduction % | C2: Rationale
A3: CRUD/Config | B3: 0.45 | C3: Boilerplate CRUD/config/scaffolding - highest AI leverage.
A4: UI Standard | B4: 0.4 | C4: Standard screens/forms/lists - strong AI leverage.
A5: Data/Migration | B5: 0.35 | C5: Schema/migrations/model wiring - good AI leverage.
A6: Infra/DevOps | B6: 0.3 | C6: CI/CD, queue, monitoring - moderate; environment-specific.
A7: Business Logic | B7: 0.3 | C7: Domain rules/handlers - moderate; human design + validation.
A8: Integration | B8: 0.25 | C8: 3rd-party (umbrella/FCM/HMRC) - lower; external contracts + testing.
A9: Complex/Critical | B9: 0.15 | C9: Payments, idempotency, compliance/matching/PAYE - lowest; correctness-critical.

Sheet WBS
A1: Phase | B1: EPIC | C1: Feature | D1: Sub-Feature | E1: Function | F1: Task Type | G1: BE | H1: Mobile | I1: Web | J1: Base Coding | K1: AI Red.% | L1: Adj Coding | M1: Total (md) | N1: Coding (md) | O1: Spec (md) | P1: PM (md) | Q1: Testing (md) | R1: Cost
A2: MVP | B2: A. Platform Hardening & Security | C2: Authentication & Access | D2: Auth hardening | E2: Rate limiting (login/forgot-pw/signed form) | F2: Business Logic | G2: 2 | H2: 0 | I2: 0 | J2: =SUM(G2:I2) | K2: =VLOOKUP(F2,'AI Factors'!$A$3:$B$9,2,FALSE) | L2: =J2*(1-K2) | M2: =IF(L2=0,0,L2/Rates!$B$15*Rates!$B$21) | N2: =M2*Rates!$B$15 | O2: =M2*Rates!$B$13 | P2: =M2*Rates!$B$14 | Q2: =M2*Rates!$B$16 | R2: =N2*Rates!$D$6+O2*Rates!$D$9+P2*Rates!$D$8+Q2*Rates!$D$7
A3: MVP | B3: A. Platform Hardening & Security | C3: Authentication & Access | D3: Auth hardening | E3: Token revoke + rotation endpoint | F3: Business Logic | G3: 2 | H3: 1 | I3: 0 | J3: =SUM(G3:I3) | K3: =VLOOKUP(F3,'AI Factors'!$A$3:$B$9,2,FALSE) | L3: =J3*(1-K3) | M3: =IF(L3=0,0,L3/Rates!$B$15*Rates!$B$21) | N3: =M3*Rates!$B$15 | O3: =M3*Rates!$B$13 | P3: =M3*Rates!$B$14 | Q3: =M3*Rates!$B$16 | R3: =N3*Rates!$D$6+O3*Rates!$D$9+P3*Rates!$D$8+Q3*Rates!$D$7
A4: MVP | B4: A. Platform Hardening & Security | C4: Authentication & Access | D4: Auth hardening | E4: Secure token storage (Keychain/Keystore) | F4: Integration | G4: 0 | H4: 2 | I4: 0 | J4: =SUM(G4:I4) | K4: =VLOOKUP(F4,'AI Factors'!$A$3:$B$9,2,FALSE) | L4: =J4*(1-K4) | M4: =IF(L4=0,0,L4/Rates!$B$15*Rates!$B$21) | N4: =M4*Rates!$B$15 | O4: =M4*Rates!$B$13 | P4: =M4*Rates!$B$14 | Q4: =M4*Rates!$B$16 | R4: =N4*Rates!$D$6+O4*Rates!$D$9+P4*Rates!$D$8+Q4*Rates!$D$7
A5: MVP | B5: A. Platform Hardening & Security | C5: Authentication & Access | D5: Auth hardening | E5: Session 401 handling + refresh | F5: Business Logic | G5: 1 | H5: 2 | I5: 0 | J5: =SUM(G5:I5) | K5: =VLOOKUP(F5,'AI Factors'!$A$3:$B$9,2,FALSE) | L5: =J5*(1-K5) | M5: =IF(L5=0,0,L5/Rates!$B$15*Rates!$B$21) | N5: =M5*Rates!$B$15 | O5: =M5*Rates!$B$13 | P5: =M5*Rates!$B$14 | Q5: =M5*Rates!$B$16 | R5: =N5*Rates!$D$6+O5*Rates!$D$9+P5*Rates!$D$8+Q5*Rates!$D$7
A6: MVP | B6: A. Platform Hardening & Security | C6: Authentication & Access | D6: Authorization | E6: Fine-grained RBAC (spatie roles/permissions) | F6: Business Logic | G6: 4 | H6: 0 | I6: 1 | J6: =SUM(G6:I6) | K6: =VLOOKUP(F6,'AI Factors'!$A$3:$B$9,2,FALSE) | L6: =J6*(1-K6) | M6: =IF(L6=0,0,L6/Rates!$B$15*Rates!$B$21) | N6: =M6*Rates!$B$15 | O6: =M6*Rates!$B$13 | P6: =M6*Rates!$B$14 | Q6: =M6*Rates!$B$16 | R6: =N6*Rates!$D$6+O6*Rates!$D$9+P6*Rates!$D$8+Q6*Rates!$D$7
A7: MVP | B7: A. Platform Hardening & Security | C7: Authentication & Access | D7: Authorization | E7: Policy coverage audit + gaps | F7: Business Logic | G7: 2 | H7: 0 | I7: 0 | J7: =SUM(G7:I7) | K7: =VLOOKUP(F7,'AI Factors'!$A$3:$B$9,2,FALSE) | L7: =J7*(1-K7) | M7: =IF(L7=0,0,L7/Rates!$B$15*Rates!$B$21) | N7: =M7*Rates!$B$15 | O7: =M7*Rates!$B$13 | P7: =M7*Rates!$B$14 | Q7: =M7*Rates!$B$16 | R7: =N7*Rates!$D$6+O7*Rates!$D$9+P7*Rates!$D$8+Q7*Rates!$D$7
A8: MVP | B8: A. Platform Hardening & Security | C8: Secrets & Config | D8: Config hardening | E8: Rotate + externalize Maps/Firebase keys | F8: Integration | G8: 1 | H8: 1 | I8: 0 | J8: =SUM(G8:I8) | K8: =VLOOKUP(F8,'AI Factors'!$A$3:$B$9,2,FALSE) | L8: =J8*(1-K8) | M8: =IF(L8=0,0,L8/Rates!$B$15*Rates!$B$21) | N8: =M8*Rates!$B$15 | O8: =M8*Rates!$B$13 | P8: =M8*Rates!$B$14 | Q8: =M8*Rates!$B$16 | R8: =N8*Rates!$D$6+O8*Rates!$D$9+P8*Rates!$D$8+Q8*Rates!$D$7
A9: MVP | B9: A. Platform Hardening & Security | C9: Secrets & Config | D9: Config hardening | E9: CORS configuration | F9: CRUD/Config | G9: 1 | H9: 0 | I9: 0 | J9: =SUM(G9:I9) | K9: =VLOOKUP(F9,'AI Factors'!$A$3:$B$9,2,FALSE) | L9: =J9*(1-K9) | M9: =IF(L9=0,0,L9/Rates!$B$15*Rates!$B$21) | N9: =M9*Rates!$B$15 | O9: =M9*Rates!$B$13 | P9: =M9*Rates!$B$14 | Q9: =M9*Rates!$B$16 | R9: =N9*Rates!$D$6+O9*Rates!$D$9+P9*Rates!$D$8+Q9*Rates!$D$7
A10: MVP | B10: A. Platform Hardening & Security | C10: Secrets & Config | D10: Config hardening | E10: .env.example + secrets management | F10: Infra/DevOps | G10: 1 | H10: 0 | I10: 0 | J10: =SUM(G10:I10) | K10: =VLOOKUP(F10,'AI Factors'!$A$3:$B$9,2,FALSE) | L10: =J10*(1-K10) | M10: =IF(L10=0,0,L10/Rates!$B$15*Rates!$B$21) | N10: =M10*Rates!$B$15 | O10: =M10*Rates!$B$13 | P10: =M10*Rates!$B$14 | Q10: =M10*Rates!$B$16 | R10: =N10*Rates!$D$6+O10*Rates!$D$9+P10*Rates!$D$8+Q10*Rates!$D$7
A11: MVP | B11: A. Platform Hardening & Security | C11: GDPR & Privacy | D11: Account lifecycle | E11: Account deletion (self-serve, cascade/anonymize) | F11: Complex/Critical | G11: 3 | H11: 1 | I11: 1 | J11: =SUM(G11:I11) | K11: =VLOOKUP(F11,'AI Factors'!$A$3:$B$9,2,FALSE) | L11: =J11*(1-K11) | M11: =IF(L11=0,0,L11/Rates!$B$15*Rates!$B$21) | N11: =M11*Rates!$B$15 | O11: =M11*Rates!$B$13 | P11: =M11*Rates!$B$14 | Q11: =M11*Rates!$B$16 | R11: =N11*Rates!$D$6+O11*Rates!$D$9+P11*Rates!$D$8+Q11*Rates!$D$7
A12: MVP | B12: A. Platform Hardening & Security | C12: GDPR & Privacy | D12: Account lifecycle | E12: Account deactivation / reactivation | F12: Business Logic | G12: 1 | H12: 1 | I12: 0 | J12: =SUM(G12:I12) | K12: =VLOOKUP(F12,'AI Factors'!$A$3:$B$9,2,FALSE) | L12: =J12*(1-K12) | M12: =IF(L12=0,0,L12/Rates!$B$15*Rates!$B$21) | N12: =M12*Rates!$B$15 | O12: =M12*Rates!$B$13 | P12: =M12*Rates!$B$14 | Q12: =M12*Rates!$B$16 | R12: =N12*Rates!$D$6+O12*Rates!$D$9+P12*Rates!$D$8+Q12*Rates!$D$7
A13: MVP | B13: A. Platform Hardening & Security | C13: GDPR & Privacy | D13: Data rights | E13: SAR data export (per-user) | F13: Complex/Critical | G13: 3 | H13: 0 | I13: 1 | J13: =SUM(G13:I13) | K13: =VLOOKUP(F13,'AI Factors'!$A$3:$B$9,2,FALSE) | L13: =J13*(1-K13) | M13: =IF(L13=0,0,L13/Rates!$B$15*Rates!$B$21) | N13: =M13*Rates!$B$15 | O13: =M13*Rates!$B$13 | P13: =M13*Rates!$B$14 | Q13: =M13*Rates!$B$16 | R13: =N13*Rates!$D$6+O13*Rates!$D$9+P13*Rates!$D$8+Q13*Rates!$D$7
... A108: Phase 2 | B108: P2-D. Advanced Compliance & Talent | C108: Talent | D108: Pools & self-serve | E108: Additional brand onboarding (multi-tenant) | F108: Business Logic | G108: 4 | H108: 0 | I108: 1 | J108: =SUM(G108:I108) | K108: =VLOOKUP(F108,'AI Factors'!$A$3:$B$9,2,FALSE) | L108: =J108*(1-K108) | M108: =IF(L108=0,0,L108/Rates!$B$15*Rates!$B$21) | N108: =M108*Rates!$B$15 | O108: =M108*Rates!$B$13 | P108: =M108*Rates!$B$14 | Q108: =M108*Rates!$B$16 | R108: =N108*Rates!$D$6+O108*Rates!$D$9+P108*Rates!$D$8+Q108*Rates!$D$7
A109: TOTAL | G109: =SUM(G2:G108) | H109: =SUM(H2:H108) | I109: =SUM(I2:I108) | J109: =SUM(J2:J108) | L109: =SUM(L2:L108) | M109: =SUM(M2:M108) | N109: =SUM(N2:N108) | O109: =SUM(O2:O108) | P109: =SUM(P2:P108) | Q109: =SUM(Q2:Q108) | R109: =SUM(R2:R108)

Sheet Summary
A1: SUMMARY
A3: MVP (delivery efficiency applied)
B4: Total md | C4: Coding md | D4: Cost
A5: Effort & cost | B5: =SUMIFS(WBS!$M$2:$M$108,WBS!$A$2:$A$108,"MVP") | C5: =SUMIFS(WBS!$N$2:$N$108,WBS!$A$2:$A$108,"MVP") | D5: =SUMIFS(WBS!$R$2:$R$108,WBS!$A$2:$A$108,"MVP")
A6: + Contingency 12% | B6: =B5*Rates!$B$19 | D6: =D5*Rates!$B$19
A7: GRAND TOTAL | B7: =B5+B6 | D7: =D5+D6
A9: PHASE 2 (delivery efficiency applied)
B10: Total md | C10: Coding md | D10: Cost
A11: Effort & cost | B11: =SUMIFS(WBS!$M$2:$M$108,WBS!$A$2:$A$108,"Phase 2") | C11: =SUMIFS(WBS!$N$2:$N$108,WBS!$A$2:$A$108,"Phase 2") | D11: =SUMIFS(WBS!$R$2:$R$108,WBS!$A$2:$A$108,"Phase 2")
A12: + Contingency 12% | B12: =B11*Rates!$B$19 | D12: =D11*Rates!$B$19
A13: GRAND TOTAL | B13: =B11+B12 | D13: =D11+D12
A15: MVP + PHASE 2 (combined)
A16: Grand total md | B16: =SUM(WBS!M2:M108)*(1+Rates!$B$19) | D16: =SUM(WBS!R2:R108)*(1+Rates!$B$19)
A18: Per-EPIC rollup | B18: Total md | C18: Cost
A19: A. Platform Hardening & Security | B19: =SUMIF(WBS!$B$2:$B$108,A19,WBS!$M$2:$M$108) | C19: =SUMIF(WBS!$B$2:$B$108,A19,WBS!$R$2:$R$108)
A20: B. Payments Integrity & Reliability | B20: =SUMIF(WBS!$B$2:$B$108,A20,WBS!$M$2:$M$108) | C20: =SUMIF(WBS!$B$2:$B$108,A20,WBS!$R$2:$R$108)
A21: C. Booking & Allocation | B21: =SUMIF(WBS!$B$2:$B$108,A21,WBS!$M$2:$M$108) | C21: =SUMIF(WBS!$B$2:$B$108,A21,WBS!$R$2:$R$108)
A22: D. Timesheet & Billing Rewire | B22: =SUMIF(WBS!$B$2:$B$108,A22,WBS!$M$2:$M$108) | C22: =SUMIF(WBS!$B$2:$B$108,A22,WBS!$R$2:$R$108)
A23: E. Availability & Matching | B23: =SUMIF(WBS!$B$2:$B$108,A23,WBS!$M$2:$M$108) | C23: =SUMIF(WBS!$B$2:$B$108,A23,WBS!$R$2:$R$108)
A24: F. Compliance (Yedi DBS/Safeguarding) | B24: =SUMIF(WBS!$B$2:$B$108,A24,WBS!$M$2:$M$108) | C24: =SUMIF(WBS!$B$2:$B$108,A24,WBS!$R$2:$R$108)
A25: G. Payroll (Umbrella) | B25: =SUMIF(WBS!$B$2:$B$108,A25,WBS!$M$2:$M$108) | C25: =SUMIF(WBS!$B$2:$B$108,A25,WBS!$R$2:$R$108)
A26: H. Reporting & Brand-Policy | B26: =SUMIF(WBS!$B$2:$B$108,A26,WBS!$M$2:$M$108) | C26: =SUMIF(WBS!$B$2:$B$108,A26,WBS!$R$2:$R$108)
A27: I. Cross-Cutting UX & Platform | B27: =SUMIF(WBS!$B$2:$B$108,A27,WBS!$M$2:$M$108) | C27: =SUMIF(WBS!$B$2:$B$108,A27,WBS!$R$2:$R$108)
A28: P2-A. Scale & Operations | B28: =SUMIF(WBS!$B$2:$B$108,A28,WBS!$M$2:$M$108) | C28: =SUMIF(WBS!$B$2:$B$108,A28,WBS!$R$2:$R$108)
A29: P2-B. Revenue & Payments | B29: =SUMIF(WBS!$B$2:$B$108,A29,WBS!$M$2:$M$108) | C29: =SUMIF(WBS!$B$2:$B$108,A29,WBS!$R$2:$R$108)
A30: P2-C. Growth & Intelligence | B30: =SUMIF(WBS!$B$2:$B$108,A30,WBS!$M$2:$M$108) | C30: =SUMIF(WBS!$B$2:$B$108,A30,WBS!$R$2:$R$108)
A31: P2-D. Advanced Compliance & Talent | B31: =SUMIF(WBS!$B$2:$B$108,A31,WBS!$M$2:$M$108) | C31: =SUMIF(WBS!$B$2:$B$108,A31,WBS!$R$2:$R$108)

Sheet Missing-Features Checklist
A1: Category | B1: Commonly-missed item | C1: In WBS? | D1: Where / Note
A2: Account | B2: Account deletion (self-serve) | C2: Yes | D2: MVP EPIC A
A3: Account | B3: Deactivation/reactivation | C3: Yes | D3: MVP EPIC A
A4: GDPR | B4: Data export / SAR | C4: Yes | D4: MVP EPIC A
A5: GDPR | B5: Right to erasure + retention | C5: Yes | D5: MVP EPIC A
A6: GDPR | B6: Consent + Terms/Privacy | C6: Yes | D6: MVP EPIC A
A7: GDPR | B7: PII scrubbing logs/audits | C7: Yes | D7: MVP EPIC A
A8: Discovery | B8: Search & filter | C8: Yes | D8: MVP EPIC I
A9: UX | B9: Empty/error/loading states | C9: Yes | D9: MVP EPIC I
A10: UX | B10: Onboarding / first-run | C10: Yes | D10: MVP EPIC I
A11: UX | B11: Offline handling | C11: Yes | D11: MVP EPIC I
A12: UX | B12: Pagination | C12: Yes | D12: MVP EPIC I
... A28: Compliance | B28: Full DBS Update Service | C28: Yes (P2) | D28: Phase 2 P2-D

Sheet Self-Review
A1: SELF-REVIEW CHECKLIST - before submitting
A2: Done? | B2: Check | C2: Owner
A3: [ ] | B3: Every row has Phase (MVP/Phase 2), EPIC->Feature->Sub-Feature->Function, a Task Type and non-zero estimate.
A4: [ ] | B4: Delivery Efficiency factor (0.70) is a CONSCIOUS client-directed cut; risk acknowledged; sensitivity at 0.85 reviewed.
A5: [ ] | B5: AI reduction only via 'AI Factors'; efficiency factor applied once, globally (not double-counted).
A6: [ ] | B6: Effort ratio 10/10/50/30 sums to 100%; Testing only in ratio (not separate coding rows).
A7: [ ] | B7: MVP timeline 1.5-2 months requires a larger concurrent team - staffing confirmed feasible.
A8: [ ] | B8: Correctness-critical items (payments, compliance gate, PAYE, matching) still LOW AI reduction despite the cut.
A9: [ ] | B9: Missing-Features checklist reviewed; MVP vs Phase 2 placement agreed.
A10: [ ] | B10: GDPR must-haves in MVP; scale/PAYE/refunds/full-DBS in Phase 2.
A11: [ ] | B11: Rates sheet is single source of truth; no hard-coded costs; currency confirmed (USD vs GBP).
A12: [ ] | B12: Critical path respected: idempotency + timesheet before billing rewire; compliance model before gate.
A13: [ ] | B13: Phase 2 total is indicative (roadmap) - to be re-confirmed nearer the time.
A14: [ ] | B14: Grand totals reconcile with the compressed target; contingency reflects brownfield + external-dependency risk.
A15: [ ] | B15: Discipline split staffable (enough Flutter/Mobile capacity for the compressed schedule).
